pytknvim/__init__.py
pytknvim/ui_bridge.py
pytknvim/tk_ui.py
pytknvim/tarruda.py
pytknvim/util.py
pytknvim/tk_util.py
pytknvim/screen.py
pytknvim/tests/__init__.py
pytknvim/tests/test_integration.py
pytknvim/tests/util.py
pytknvim-0.1.6.dist-info/RECORD
pytknvim-0.1.6.dist-info/METADATA
pytknvim-0.1.6.dist-info/metadata.json
pytknvim-0.1.6.dist-info/entry_points.txt
pytknvim-0.1.6.dist-info/top_level.txt
pytknvim-0.1.6.dist-info/DESCRIPTION.rst
pytknvim-0.1.6.dist-info/pbr.json
pytknvim-0.1.6.dist-info/WHEEL
