Metadata-Version: 2.0
Name: pytknvim
Version: 0.1.6
Summary: tkinter text widget using neovim
Home-page: https://github.com/timeyyy/pytknvim
Author: timeyyy
Author-email: tim_eichler@hotmail.com
License: BSD3
Keywords: tkinter text neovim vim edit
Platform: UNKNOWN
Classifier: Development Status :: 4 - Beta
Classifier: Intended Audience :: Developers
Classifier: License :: OSI Approved :: BSD License
Classifier: Programming Language :: Python :: 3
Requires-Dist: neovim (>=0.1.3)
